LICENSE
README.md
requirements.txt
setup.py
termsquery.py
test_termsquery.py
termsquery.egg-info/PKG-INFO
termsquery.egg-info/SOURCES.txt
termsquery.egg-info/dependency_links.txt
termsquery.egg-info/top_level.txt