Metadata-Version: 2.1
Name: termsquery
Version: 0.2
Summary: Terms boolean expressions to query containers
Home-page: https://github.com/gruzovator/termsquery
Author: gruzovator
Author-email: gruzovator@github.com
License: MIT
Keywords: boolean expression,logic,expression parser,tagging,tag
Platform: UNKNOWN
Requires-Python: >=3
